acdcreate
