Metadata-Version: 2.1
Name: acdcreate
Version: 2.8
Summary: Быстрая библиотека для создания файлов
Home-page: UNKNOWN
Author: Sasibacka
Author-email: sergeycikkatkovcik@gmail.com
License: UNKNOWN
Platform: UNKNOWN
